[
    {
        "lat": 40.4351112,
        "lon": -79.9471507
    },
    {
        "lat": 40.424934,
        "lon": -79.9199497
    },
    {
        "lat": 40.4454168,
        "lon": -79.9294755
    },
    {
        "lat": 40.4323578,
        "lon": -79.9231497
    },
    {
        "lat": 40.4396591,
        "lon": -79.9253622
    },
    {
        "lat": 40.4118054,
        "lon": -79.9228067
    },
    {
        "lat": 40.436234,
        "lon": -79.9191103
    },
    {
        "lat": 40.4422747,
        "lon": -79.9171622
    },
    {
        "lat": 40.4401478,
        "lon": -79.9422539
    },
    {
        "lat": 40.429537,
        "lon": -79.9207923
    },
    {
        "lat": 40.4227492,
        "lon": -79.9120975
    },
    {
        "lat": 40.4362018,
        "lon": -79.9136391
    },
    {
        "lat": 40.4419218,
        "lon": -79.9294865
    },
    {
        "lat": 40.4472435,
        "lon": -79.9353562
    },
    {
        "lat": 40.4421394,
        "lon": -79.9235076
    },
    {
        "lat": 40.4326188,
        "lon": -79.9275492
    },
    {
        "lat": 40.4207991,
        "lon": -79.9215237
    },
    {
        "lat": 40.4326265,
        "lon": -79.9151132
    },
    {
        "lat": 40.427918,
        "lon": -79.9160992
    },
    {
        "lat": 40.4267844,
        "lon": -79.9232435
    },
    {
        "lat": 40.4454217,
        "lon": -79.9127256
    },
    {
        "lat": 40.4363141,
        "lon": -79.9464724
    },
    {
        "lat": 40.4181544,
        "lon": -79.9242429
    },
    {
        "lat": 40.417144,
        "lon": -79.919486
    },
    {
        "lat": 40.4453377,
        "lon": -79.9349006
    },
    {
        "lat": 40.440934,
        "lon": -79.9344431
    }
]